{"nodes": ["0", "3", "12", "38", "40", "58", "65", "67", "78", "86", "105", "111", "116", "134", "148", "150", "217", "219", "247", "263", "275", "283", "299", "310", "317", "325", "355", "378", "391", "402", "419", "420", "427", "450", "462", "468", "470", "471", "478", "482", "10", "139", "166", "242", "268", "300", "304", "360", "410", "413", "368", "400", "405", "426", "445", "451", "456", "19", "47", "186", "377", "89", "463", "503", "508", "556", "587", "621", "669", "686", "701", "754", "765", "856", "902", "927", "980", "570", "591", "606", "615", "652", "673", "832", "862", "893", "901", "949", "981", "659", "662", "720", "737", "784", "913", "931", "963", "706", "785", "719"], "edges": [{"source": "556", "target": "662"}, {"source": "556", "target": "902"}, {"source": "556", "target": "652"}, {"source": "556", "target": "784"}, {"source": "556", "target": "913"}, {"source": "556", "target": "669"}, {"source": "556", "target": "927"}, {"source": "556", "target": "673"}, {"source": "556", "target": "686"}, {"source": "556", "target": "949"}, {"source": "556", "target": "701"}, {"source": "556", "target": "832"}, {"source": "556", "target": "591"}, {"source": "556", "target": "720"}, {"source": "556", "target": "981"}, {"source": "556", "target": "856"}, {"source": "556", "target": "862"}, {"source": "556", "target": "606"}, {"source": "556", "target": "737"}, {"source": "556", "target": "615"}, {"source": "556", "target": "503"}, {"source": "556", "target": "508"}, {"source": "556", "target": "893"}, {"source": "662", "target": "901"}, {"source": "662", "target": "893"}, {"source": "662", "target": "659"}, {"source": "662", "target": "669"}, {"source": "662", "target": "931"}, {"source": "662", "target": "686"}, {"source": "662", "target": "949"}, {"source": "662", "target": "701"}, {"source": "662", "target": "587"}, {"source": "662", "target": "591"}, {"source": "662", "target": "719"}, {"source": "662", "target": "720"}, {"source": "662", "target": "980"}, {"source": "662", "target": "981"}, {"source": "662", "target": "606"}, {"source": "662", "target": "737"}, {"source": "662", "target": "615"}, {"source": "662", "target": "754"}, {"source": "662", "target": "503"}, {"source": "662", "target": "508"}, {"source": "662", "target": "765"}, {"source": "150", "target": "419"}, {"source": "150", "target": "0"}, {"source": "150", "target": "263"}, {"source": "150", "target": "391"}, {"source": "150", "target": "139"}, {"source": "150", "target": "12"}, {"source": "150", "target": "268"}, {"source": "150", "target": "148"}, {"source": "150", "target": "413"}, {"source": "150", "target": "40"}, {"source": "150", "target": "426"}, {"source": "150", "target": "299"}, {"source": "150", "target": "300"}, {"source": "150", "target": "186"}, {"source": "150", "target": "317"}, {"source": "150", "target": "65"}, {"source": "150", "target": "450"}, {"source": "150", "target": "451"}, {"source": "150", "target": "78"}, {"source": "150", "target": "468"}, {"source": "150", "target": "470"}, {"source": "150", "target": "471"}, {"source": "150", "target": "217"}, {"source": "150", "target": "89"}, {"source": "150", "target": "219"}, {"source": "150", "target": "482"}, {"source": "150", "target": "111"}, {"source": "150", "target": "368"}, {"source": "150", "target": "247"}, {"source": "150", "target": "377"}, {"source": "419", "target": "0"}, {"source": "419", "target": "10"}, {"source": "419", "target": "139"}, {"source": "419", "target": "12"}, {"source": "419", "target": "283"}, {"source": "419", "target": "413"}, {"source": "419", "target": "420"}, {"source": "419", "target": "38"}, {"source": "419", "target": "166"}, {"source": "419", "target": "40"}, {"source": "419", "target": "427"}, {"source": "419", "target": "47"}, {"source": "419", "target": "310"}, {"source": "419", "target": "58"}, {"source": "419", "target": "317"}, {"source": "419", "target": "65"}, {"source": "419", "target": "450"}, {"source": "419", "target": "67"}, {"source": "419", "target": "451"}, {"source": "419", "target": "468"}, {"source": "419", "target": "86"}, {"source": "419", "target": "219"}, {"source": "419", "target": "360"}, {"source": "419", "target": "105"}, {"source": "419", "target": "111"}, {"source": "419", "target": "368"}, {"source": "419", "target": "247"}, {"source": "419", "target": "377"}, {"source": "419", "target": "378"}, {"source": "67", "target": "186"}, {"source": "67", "target": "378"}, {"source": "67", "target": "0"}, {"source": "67", "target": "3"}, {"source": "67", "target": "263"}, {"source": "67", "target": "10"}, {"source": "67", "target": "139"}, {"source": "67", "target": "268"}, {"source": "67", "target": "402"}, {"source": "67", "target": "19"}, {"source": "67", "target": "275"}, {"source": "67", "target": "413"}, {"source": "67", "target": "420"}, {"source": "67", "target": "38"}, {"source": "67", "target": "166"}, {"source": "67", "target": "40"}, {"source": "67", "target": "299"}, {"source": "67", "target": "300"}, {"source": "67", "target": "427"}, {"source": "67", "target": "310"}, {"source": "67", "target": "58"}, {"source": "67", "target": "65"}, {"source": "67", "target": "450"}, {"source": "67", "target": "451"}, {"source": "67", "target": "325"}, {"source": "67", "target": "456"}, {"source": "67", "target": "462"}, {"source": "67", "target": "89"}, {"source": "67", "target": "219"}, {"source": "67", "target": "360"}, {"source": "67", "target": "105"}, {"source": "67", "target": "368"}, {"source": "67", "target": "242"}, {"source": "67", "target": "247"}, {"source": "67", "target": "377"}, {"source": "186", "target": "3"}, {"source": "186", "target": "263"}, {"source": "186", "target": "10"}, {"source": "186", "target": "12"}, {"source": "186", "target": "268"}, {"source": "186", "target": "400"}, {"source": "186", "target": "402"}, {"source": "186", "target": "19"}, {"source": "186", "target": "148"}, {"source": "186", "target": "275"}, {"source": "186", "target": "410"}, {"source": "186", "target": "283"}, {"source": "186", "target": "420"}, {"source": "186", "target": "38"}, {"source": "186", "target": "166"}, {"source": "186", "target": "40"}, {"source": "186", "target": "299"}, {"source": "186", "target": "300"}, {"source": "186", "target": "427"}, {"source": "186", "target": "47"}, {"source": "186", "target": "310"}, {"source": "186", "target": "58"}, {"source": "186", "target": "317"}, {"source": "186", "target": "445"}, {"source": "186", "target": "450"}, {"source": "186", "target": "462"}, {"source": "186", "target": "463"}, {"source": "186", "target": "471"}, {"source": "186", "target": "217"}, {"source": "186", "target": "355"}, {"source": "186", "target": "105"}, {"source": "186", "target": "242"}, {"source": "737", "target": "931"}, {"source": "737", "target": "901"}, {"source": "737", "target": "784"}, {"source": "737", "target": "913"}, {"source": "737", "target": "669"}, {"source": "737", "target": "927"}, {"source": "737", "target": "673"}, {"source": "737", "target": "686"}, {"source": "737", "target": "949"}, {"source": "737", "target": "570"}, {"source": "737", "target": "701"}, {"source": "737", "target": "706"}, {"source": "737", "target": "963"}, {"source": "737", "target": "591"}, {"source": "737", "target": "720"}, {"source": "737", "target": "981"}, {"source": "737", "target": "856"}, {"source": "737", "target": "862"}, {"source": "737", "target": "621"}, {"source": "737", "target": "754"}, {"source": "737", "target": "503"}, {"source": "737", "target": "508"}, {"source": "931", "target": "901"}, {"source": "931", "target": "652"}, {"source": "931", "target": "893"}, {"source": "931", "target": "784"}, {"source": "931", "target": "785"}, {"source": "931", "target": "659"}, {"source": "931", "target": "669"}, {"source": "931", "target": "673"}, {"source": "931", "target": "686"}, {"source": "931", "target": "949"}, {"source": "931", "target": "570"}, {"source": "931", "target": "701"}, {"source": "931", "target": "706"}, {"source": "931", "target": "587"}, {"source": "931", "target": "591"}, {"source": "931", "target": "719"}, {"source": "931", "target": "720"}, {"source": "931", "target": "981"}, {"source": "931", "target": "862"}, {"source": "931", "target": "615"}, {"source": "931", "target": "621"}, {"source": "931", "target": "503"}, {"source": "931", "target": "508"}, {"source": "931", "target": "765"}, {"source": "765", "target": "570"}, {"source": "765", "target": "901"}, {"source": "765", "target": "902"}, {"source": "765", "target": "659"}, {"source": "765", "target": "669"}, {"source": "765", "target": "927"}, {"source": "765", "target": "949"}, {"source": "765", "target": "832"}, {"source": "765", "target": "963"}, {"source": "765", "target": "587"}, {"source": "765", "target": "591"}, {"source": "765", "target": "719"}, {"source": "765", "target": "720"}, {"source": "765", "target": "980"}, {"source": "765", "target": "981"}, {"source": "765", "target": "862"}, {"source": "765", "target": "621"}, {"source": "765", "target": "754"}, {"source": "765", "target": "503"}, {"source": "765", "target": "508"}, {"source": "570", "target": "901"}, {"source": "570", "target": "902"}, {"source": "570", "target": "893"}, {"source": "570", "target": "784"}, {"source": "570", "target": "659"}, {"source": "570", "target": "669"}, {"source": "570", "target": "927"}, {"source": "570", "target": "673"}, {"source": "570", "target": "949"}, {"source": "570", "target": "701"}, {"source": "570", "target": "832"}, {"source": "570", "target": "706"}, {"source": "570", "target": "587"}, {"source": "570", "target": "591"}, {"source": "570", "target": "719"}, {"source": "570", "target": "720"}, {"source": "570", "target": "856"}, {"source": "570", "target": "621"}, {"source": "570", "target": "754"}, {"source": "378", "target": "0"}, {"source": "378", "target": "3"}, {"source": "378", "target": "263"}, {"source": "378", "target": "391"}, {"source": "378", "target": "10"}, {"source": "378", "target": "12"}, {"source": "378", "target": "268"}, {"source": "378", "target": "402"}, {"source": "378", "target": "275"}, {"source": "378", "target": "148"}, {"source": "378", "target": "420"}, {"source": "378", "target": "38"}, {"source": "378", "target": "40"}, {"source": "378", "target": "427"}, {"source": "378", "target": "304"}, {"source": "378", "target": "445"}, {"source": "378", "target": "65"}, {"source": "378", "target": "451"}, {"source": "378", "target": "325"}, {"source": "378", "target": "456"}, {"source": "378", "target": "462"}, {"source": "378", "target": "463"}, {"source": "378", "target": "86"}, {"source": "378", "target": "470"}, {"source": "378", "target": "217"}, {"source": "378", "target": "219"}, {"source": "378", "target": "478"}, {"source": "378", "target": "482"}, {"source": "378", "target": "111"}, {"source": "378", "target": "242"}, {"source": "378", "target": "377"}, {"source": "701", "target": "659"}, {"source": "701", "target": "901"}, {"source": "701", "target": "902"}, {"source": "701", "target": "652"}, {"source": "701", "target": "784"}, {"source": "701", "target": "673"}, {"source": "701", "target": "686"}, {"source": "701", "target": "832"}, {"source": "701", "target": "706"}, {"source": "701", "target": "587"}, {"source": "701", "target": "862"}, {"source": "701", "target": "606"}, {"source": "701", "target": "615"}, {"source": "701", "target": "621"}, {"source": "701", "target": "754"}, {"source": "701", "target": "503"}, {"source": "701", "target": "508"}, {"source": "659", "target": "901"}, {"source": "659", "target": "902"}, {"source": "659", "target": "652"}, {"source": "659", "target": "785"}, {"source": "659", "target": "913"}, {"source": "659", "target": "927"}, {"source": "659", "target": "686"}, {"source": "659", "target": "949"}, {"source": "659", "target": "832"}, {"source": "659", "target": "706"}, {"source": "659", "target": "963"}, {"source": "659", "target": "587"}, {"source": "659", "target": "591"}, {"source": "659", "target": "720"}, {"source": "659", "target": "980"}, {"source": "659", "target": "606"}, {"source": "659", "target": "615"}, {"source": "659", "target": "621"}, {"source": "659", "target": "503"}, {"source": "949", "target": "784"}, {"source": "949", "target": "901"}, {"source": "949", "target": "902"}, {"source": "949", "target": "913"}, {"source": "949", "target": "669"}, {"source": "949", "target": "927"}, {"source": "949", "target": "963"}, {"source": "949", "target": "719"}, {"source": "949", "target": "720"}, {"source": "949", "target": "862"}, {"source": "949", "target": "606"}, {"source": "949", "target": "621"}, {"source": "949", "target": "754"}, {"source": "949", "target": "508"}, {"source": "784", "target": "901"}, {"source": "784", "target": "902"}, {"source": "784", "target": "913"}, {"source": "784", "target": "669"}, {"source": "784", "target": "927"}, {"source": "784", "target": "673"}, {"source": "784", "target": "686"}, {"source": "784", "target": "832"}, {"source": "784", "target": "963"}, {"source": "784", "target": "980"}, {"source": "784", "target": "981"}, {"source": "784", "target": "862"}, {"source": "784", "target": "606"}, {"source": "784", "target": "754"}, {"source": "784", "target": "503"}, {"source": "784", "target": "508"}, {"source": "247", "target": "139"}, {"source": "247", "target": "0"}, {"source": "247", "target": "3"}, {"source": "247", "target": "263"}, {"source": "247", "target": "391"}, {"source": "247", "target": "10"}, {"source": "247", "target": "268"}, {"source": "247", "target": "19"}, {"source": "247", "target": "405"}, {"source": "247", "target": "413"}, {"source": "247", "target": "38"}, {"source": "247", "target": "299"}, {"source": "247", "target": "300"}, {"source": "247", "target": "427"}, {"source": "247", "target": "47"}, {"source": "247", "target": "58"}, {"source": "247", "target": "317"}, {"source": "247", "target": "65"}, {"source": "247", "target": "451"}, {"source": "247", "target": "456"}, {"source": "247", "target": "78"}, {"source": "247", "target": "462"}, {"source": "247", "target": "463"}, {"source": "247", "target": "468"}, {"source": "247", "target": "86"}, {"source": "247", "target": "89"}, {"source": "247", "target": "219"}, {"source": "247", "target": "478"}, {"source": "247", "target": "482"}, {"source": "247", "target": "105"}, {"source": "139", "target": "134"}, {"source": "139", "target": "263"}, {"source": "139", "target": "12"}, {"source": "139", "target": "268"}, {"source": "139", "target": "400"}, {"source": "139", "target": "402"}, {"source": "139", "target": "19"}, {"source": "139", "target": "275"}, {"source": "139", "target": "410"}, {"source": "139", "target": "283"}, {"source": "139", "target": "413"}, {"source": "139", "target": "420"}, {"source": "139", "target": "166"}, {"source": "139", "target": "426"}, {"source": "139", "target": "299"}, {"source": "139", "target": "427"}, {"source": "139", "target": "47"}, {"source": "139", "target": "304"}, {"source": "139", "target": "65"}, {"source": "139", "target": "325"}, {"source": "139", "target": "78"}, {"source": "139", "target": "463"}, {"source": "139", "target": "468"}, {"source": "139", "target": "86"}, {"source": "139", "target": "470"}, {"source": "139", "target": "217"}, {"source": "139", "target": "219"}, {"source": "139", "target": "360"}, {"source": "139", "target": "105"}, {"source": "139", "target": "242"}, {"source": "139", "target": "116"}, {"source": "139", "target": "377"}, {"source": "360", "target": "463"}, {"source": "360", "target": "134"}, {"source": "360", "target": "263"}, {"source": "360", "target": "10"}, {"source": "360", "target": "12"}, {"source": "360", "target": "268"}, {"source": "360", "target": "400"}, {"source": "360", "target": "410"}, {"source": "360", "target": "38"}, {"source": "360", "target": "166"}, {"source": "360", "target": "426"}, {"source": "360", "target": "299"}, {"source": "360", "target": "304"}, {"source": "360", "target": "310"}, {"source": "360", "target": "58"}, {"source": "360", "target": "317"}, {"source": "360", "target": "65"}, {"source": "360", "target": "451"}, {"source": "360", "target": "325"}, {"source": "360", "target": "462"}, {"source": "360", "target": "468"}, {"source": "360", "target": "470"}, {"source": "360", "target": "217"}, {"source": "360", "target": "482"}, {"source": "360", "target": "105"}, {"source": "360", "target": "111"}, {"source": "360", "target": "377"}, {"source": "463", "target": "134"}, {"source": "463", "target": "263"}, {"source": "463", "target": "12"}, {"source": "463", "target": "268"}, {"source": "463", "target": "402"}, {"source": "463", "target": "19"}, {"source": "463", "target": "410"}, {"source": "463", "target": "283"}, {"source": "463", "target": "413"}, {"source": "463", "target": "420"}, {"source": "463", "target": "38"}, {"source": "463", "target": "40"}, {"source": "463", "target": "426"}, {"source": "463", "target": "299"}, {"source": "463", "target": "300"}, {"source": "463", "target": "47"}, {"source": "463", "target": "310"}, {"source": "463", "target": "317"}, {"source": "463", "target": "445"}, {"source": "463", "target": "325"}, {"source": "463", "target": "78"}, {"source": "463", "target": "462"}, {"source": "463", "target": "86"}, {"source": "463", "target": "470"}, {"source": "463", "target": "89"}, {"source": "463", "target": "219"}, {"source": "463", "target": "478"}, {"source": "463", "target": "482"}, {"source": "463", "target": "111"}, {"source": "463", "target": "368"}, {"source": "463", "target": "242"}, {"source": "268", "target": "400"}, {"source": "268", "target": "134"}, {"source": "268", "target": "3"}, {"source": "268", "target": "263"}, {"source": "268", "target": "10"}, {"source": "268", "target": "12"}, {"source": "268", "target": "402"}, {"source": "268", "target": "275"}, {"source": "268", "target": "405"}, {"source": "268", "target": "410"}, {"source": "268", "target": "38"}, {"source": "268", "target": "166"}, {"source": "268", "target": "304"}, {"source": "268", "target": "58"}, {"source": "268", "target": "317"}, {"source": "268", "target": "445"}, {"source": "268", "target": "65"}, {"source": "268", "target": "450"}, {"source": "268", "target": "451"}, {"source": "268", "target": "325"}, {"source": "268", "target": "456"}, {"source": "268", "target": "78"}, {"source": "268", "target": "86"}, {"source": "268", "target": "470"}, {"source": "268", "target": "471"}, {"source": "268", "target": "89"}, {"source": "268", "target": "482"}, {"source": "268", "target": "105"}, {"source": "268", "target": "111"}, {"source": "268", "target": "377"}, {"source": "400", "target": "134"}, {"source": "400", "target": "391"}, {"source": "400", "target": "10"}, {"source": "400", "target": "402"}, {"source": "400", "target": "405"}, {"source": "400", "target": "410"}, {"source": "400", "target": "413"}, {"source": "400", "target": "420"}, {"source": "400", "target": "38"}, {"source": "400", "target": "166"}, {"source": "400", "target": "40"}, {"source": "400", "target": "299"}, {"source": "400", "target": "300"}, {"source": "400", "target": "47"}, {"source": "400", "target": "304"}, {"source": "400", "target": "317"}, {"source": "400", "target": "445"}, {"source": "400", "target": "65"}, {"source": "400", "target": "450"}, {"source": "400", "target": "325"}, {"source": "400", "target": "78"}, {"source": "400", "target": "86"}, {"source": "400", "target": "470"}, {"source": "400", "target": "471"}, {"source": "400", "target": "217"}, {"source": "400", "target": "89"}, {"source": "400", "target": "368"}, {"source": "400", "target": "242"}, {"source": "400", "target": "116"}, {"source": "400", "target": "377"}, {"source": "300", "target": "47"}, {"source": "300", "target": "263"}, {"source": "300", "target": "10"}, {"source": "300", "target": "148"}, {"source": "300", "target": "420"}, {"source": "300", "target": "427"}, {"source": "300", "target": "304"}, {"source": "300", "target": "58"}, {"source": "300", "target": "317"}, {"source": "300", "target": "445"}, {"source": "300", "target": "451"}, {"source": "300", "target": "78"}, {"source": "300", "target": "219"}, {"source": "300", "target": "478"}, {"source": "300", "target": "482"}, {"source": "300", "target": "105"}, {"source": "300", "target": "368"}, {"source": "300", "target": "242"}, {"source": "300", "target": "116"}, {"source": "47", "target": "426"}, {"source": "47", "target": "3"}, {"source": "47", "target": "391"}, {"source": "47", "target": "19"}, {"source": "47", "target": "148"}, {"source": "47", "target": "420"}, {"source": "47", "target": "299"}, {"source": "47", "target": "310"}, {"source": "47", "target": "65"}, {"source": "47", "target": "450"}, {"source": "47", "target": "451"}, {"source": "47", "target": "325"}, {"source": "47", "target": "78"}, {"source": "47", "target": "86"}, {"source": "47", "target": "471"}, {"source": "47", "target": "217"}, {"source": "47", "target": "89"}, {"source": "47", "target": "219"}, {"source": "47", "target": "478"}, {"source": "47", "target": "482"}, {"source": "47", "target": "355"}, {"source": "47", "target": "105"}, {"source": "47", "target": "111"}, {"source": "47", "target": "368"}, {"source": "47", "target": "116"}, {"source": "47", "target": "377"}, {"source": "65", "target": "402"}, {"source": "65", "target": "0"}, {"source": "65", "target": "3"}, {"source": "65", "target": "134"}, {"source": "65", "target": "391"}, {"source": "65", "target": "10"}, {"source": "65", "target": "12"}, {"source": "65", "target": "19"}, {"source": "65", "target": "148"}, {"source": "65", "target": "275"}, {"source": "65", "target": "413"}, {"source": "65", "target": "420"}, {"source": "65", "target": "38"}, {"source": "65", "target": "166"}, {"source": "65", "target": "427"}, {"source": "65", "target": "451"}, {"source": "65", "target": "325"}, {"source": "65", "target": "217"}, {"source": "65", "target": "478"}, {"source": "65", "target": "482"}, {"source": "65", "target": "355"}, {"source": "65", "target": "105"}, {"source": "65", "target": "111"}, {"source": "65", "target": "368"}, {"source": "65", "target": "116"}, {"source": "402", "target": "0"}, {"source": "402", "target": "3"}, {"source": "402", "target": "263"}, {"source": "402", "target": "391"}, {"source": "402", "target": "10"}, {"source": "402", "target": "19"}, {"source": "402", "target": "275"}, {"source": "402", "target": "38"}, {"source": "402", "target": "166"}, {"source": "402", "target": "427"}, {"source": "402", "target": "304"}, {"source": "402", "target": "310"}, {"source": "402", "target": "445"}, {"source": "402", "target": "450"}, {"source": "402", "target": "451"}, {"source": "402", "target": "456"}, {"source": "402", "target": "78"}, {"source": "402", "target": "462"}, {"source": "402", "target": "468"}, {"source": "402", "target": "86"}, {"source": "402", "target": "478"}, {"source": "402", "target": "355"}, {"source": "402", "target": "116"}, {"source": "134", "target": "0"}, {"source": "134", "target": "263"}, {"source": "134", "target": "391"}, {"source": "134", "target": "12"}, {"source": "134", "target": "148"}, {"source": "134", "target": "405"}, {"source": "134", "target": "420"}, {"source": "134", "target": "38"}, {"source": "134", "target": "166"}, {"source": "134", "target": "426"}, {"source": "134", "target": "299"}, {"source": "134", "target": "427"}, {"source": "134", "target": "310"}, {"source": "134", "target": "317"}, {"source": "134", "target": "445"}, {"source": "134", "target": "450"}, {"source": "134", "target": "451"}, {"source": "134", "target": "325"}, {"source": "134", "target": "78"}, {"source": "134", "target": "462"}, {"source": "134", "target": "86"}, {"source": "134", "target": "470"}, {"source": "134", "target": "89"}, {"source": "134", "target": "478"}, {"source": "134", "target": "482"}, {"source": "134", "target": "105"}, {"source": "40", "target": "325"}, {"source": "40", "target": "0"}, {"source": "40", "target": "263"}, {"source": "40", "target": "391"}, {"source": "40", "target": "275"}, {"source": "40", "target": "405"}, {"source": "40", "target": "283"}, {"source": "40", "target": "38"}, {"source": "40", "target": "427"}, {"source": "40", "target": "304"}, {"source": "40", "target": "310"}, {"source": "40", "target": "58"}, {"source": "40", "target": "445"}, {"source": "40", "target": "451"}, {"source": "40", "target": "78"}, {"source": "40", "target": "468"}, {"source": "40", "target": "86"}, {"source": "40", "target": "470"}, {"source": "40", "target": "217"}, {"source": "40", "target": "89"}, {"source": "40", "target": "219"}, {"source": "40", "target": "478"}, {"source": "40", "target": "355"}, {"source": "40", "target": "105"}, {"source": "40", "target": "368"}, {"source": "40", "target": "377"}, {"source": "325", "target": "0"}, {"source": "325", "target": "3"}, {"source": "325", "target": "391"}, {"source": "325", "target": "12"}, {"source": "325", "target": "19"}, {"source": "325", "target": "275"}, {"source": "325", "target": "405"}, {"source": "325", "target": "410"}, {"source": "325", "target": "413"}, {"source": "325", "target": "420"}, {"source": "325", "target": "426"}, {"source": "325", "target": "427"}, {"source": "325", "target": "304"}, {"source": "325", "target": "310"}, {"source": "325", "target": "58"}, {"source": "325", "target": "450"}, {"source": "325", "target": "451"}, {"source": "325", "target": "456"}, {"source": "325", "target": "470"}, {"source": "325", "target": "219"}, {"source": "325", "target": "478"}, {"source": "325", "target": "116"}, {"source": "38", "target": "283"}, {"source": "38", "target": "0"}, {"source": "38", "target": "3"}, {"source": "38", "target": "263"}, {"source": "38", "target": "12"}, {"source": "38", "target": "405"}, {"source": "38", "target": "413"}, {"source": "38", "target": "420"}, {"source": "38", "target": "426"}, {"source": "38", "target": "299"}, {"source": "38", "target": "427"}, {"source": "38", "target": "304"}, {"source": "38", "target": "310"}, {"source": "38", "target": "445"}, {"source": "38", "target": "456"}, {"source": "38", "target": "462"}, {"source": "38", "target": "468"}, {"source": "38", "target": "86"}, {"source": "38", "target": "217"}, {"source": "38", "target": "219"}, {"source": "38", "target": "478"}, {"source": "38", "target": "482"}, {"source": "38", "target": "368"}, {"source": "38", "target": "242"}, {"source": "38", "target": "116"}, {"source": "38", "target": "377"}, {"source": "283", "target": "0"}, {"source": "283", "target": "3"}, {"source": "283", "target": "263"}, {"source": "283", "target": "12"}, {"source": "283", "target": "275"}, {"source": "283", "target": "148"}, {"source": "283", "target": "405"}, {"source": "283", "target": "410"}, {"source": "283", "target": "413"}, {"source": "283", "target": "420"}, {"source": "283", "target": "299"}, {"source": "283", "target": "427"}, {"source": "283", "target": "304"}, {"source": "283", "target": "317"}, {"source": "283", "target": "450"}, {"source": "283", "target": "451"}, {"source": "283", "target": "456"}, {"source": "283", "target": "86"}, {"source": "283", "target": "89"}, {"source": "283", "target": "219"}, {"source": "283", "target": "482"}, {"source": "283", "target": "355"}, {"source": "283", "target": "105"}, {"source": "283", "target": "111"}, {"source": "283", "target": "368"}, {"source": "283", "target": "242"}, {"source": "283", "target": "116"}, {"source": "78", "target": "19"}, {"source": "78", "target": "0"}, {"source": "78", "target": "3"}, {"source": "78", "target": "10"}, {"source": "78", "target": "12"}, {"source": "78", "target": "275"}, {"source": "78", "target": "405"}, {"source": "78", "target": "413"}, {"source": "78", "target": "420"}, {"source": "78", "target": "166"}, {"source": "78", "target": "426"}, {"source": "78", "target": "299"}, {"source": "78", "target": "427"}, {"source": "78", "target": "58"}, {"source": "78", "target": "317"}, {"source": "78", "target": "445"}, {"source": "78", "target": "456"}, {"source": "78", "target": "462"}, {"source": "78", "target": "468"}, {"source": "78", "target": "86"}, {"source": "78", "target": "470"}, {"source": "78", "target": "217"}, {"source": "78", "target": "219"}, {"source": "78", "target": "478"}, {"source": "78", "target": "482"}, {"source": "78", "target": "355"}, {"source": "78", "target": "105"}, {"source": "78", "target": "111"}, {"source": "78", "target": "368"}, {"source": "19", "target": "3"}, {"source": "19", "target": "391"}, {"source": "19", "target": "10"}, {"source": "19", "target": "413"}, {"source": "19", "target": "304"}, {"source": "19", "target": "317"}, {"source": "19", "target": "445"}, {"source": "19", "target": "451"}, {"source": "19", "target": "456"}, {"source": "19", "target": "468"}, {"source": "19", "target": "471"}, {"source": "19", "target": "217"}, {"source": "19", "target": "89"}, {"source": "19", "target": "478"}, {"source": "19", "target": "482"}, {"source": "19", "target": "355"}, {"source": "19", "target": "368"}, {"source": "19", "target": "242"}, {"source": "19", "target": "116"}, {"source": "19", "target": "377"}, {"source": "587", "target": "856"}, {"source": "587", "target": "902"}, {"source": "587", "target": "652"}, {"source": "587", "target": "785"}, {"source": "587", "target": "913"}, {"source": "587", "target": "669"}, {"source": "587", "target": "927"}, {"source": "587", "target": "673"}, {"source": "587", "target": "832"}, {"source": "587", "target": "963"}, {"source": "587", "target": "591"}, {"source": "587", "target": "981"}, {"source": "587", "target": "606"}, {"source": "587", "target": "615"}, {"source": "587", "target": "621"}, {"source": "587", "target": "754"}, {"source": "587", "target": "503"}, {"source": "587", "target": "508"}, {"source": "856", "target": "673"}, {"source": "856", "target": "706"}, {"source": "856", "target": "963"}, {"source": "856", "target": "901"}, {"source": "856", "target": "902"}, {"source": "856", "target": "615"}, {"source": "856", "target": "893"}, {"source": "856", "target": "720"}, {"source": "856", "target": "913"}, {"source": "856", "target": "754"}, {"source": "856", "target": "669"}, {"source": "856", "target": "862"}, {"source": "856", "target": "927"}, {"source": "12", "target": "242"}, {"source": "12", "target": "0"}, {"source": "12", "target": "10"}, {"source": "12", "target": "148"}, {"source": "12", "target": "413"}, {"source": "12", "target": "420"}, {"source": "12", "target": "166"}, {"source": "12", "target": "299"}, {"source": "12", "target": "310"}, {"source": "12", "target": "317"}, {"source": "12", "target": "450"}, {"source": "12", "target": "451"}, {"source": "12", "target": "462"}, {"source": "12", "target": "468"}, {"source": "12", "target": "470"}, {"source": "12", "target": "471"}, {"source": "12", "target": "217"}, {"source": "12", "target": "89"}, {"source": "12", "target": "219"}, {"source": "12", "target": "482"}, {"source": "12", "target": "355"}, {"source": "12", "target": "105"}, {"source": "12", "target": "111"}, {"source": "12", "target": "368"}, {"source": "12", "target": "116"}, {"source": "242", "target": "3"}, {"source": "242", "target": "263"}, {"source": "242", "target": "391"}, {"source": "242", "target": "10"}, {"source": "242", "target": "148"}, {"source": "242", "target": "275"}, {"source": "242", "target": "405"}, {"source": "242", "target": "410"}, {"source": "242", "target": "299"}, {"source": "242", "target": "427"}, {"source": "242", "target": "310"}, {"source": "242", "target": "58"}, {"source": "242", "target": "317"}, {"source": "242", "target": "451"}, {"source": "242", "target": "86"}, {"source": "242", "target": "217"}, {"source": "242", "target": "89"}, {"source": "242", "target": "478"}, {"source": "242", "target": "482"}, {"source": "242", "target": "355"}, {"source": "242", "target": "105"}, {"source": "242", "target": "116"}, {"source": "242", "target": "377"}, {"source": "754", "target": "706"}, {"source": "754", "target": "902"}, {"source": "754", "target": "893"}, {"source": "754", "target": "785"}, {"source": "754", "target": "927"}, {"source": "754", "target": "832"}, {"source": "754", "target": "591"}, {"source": "754", "target": "980"}, {"source": "754", "target": "981"}, {"source": "754", "target": "862"}, {"source": "754", "target": "615"}, {"source": "754", "target": "621"}, {"source": "754", "target": "503"}, {"source": "754", "target": "508"}, {"source": "706", "target": "902"}, {"source": "706", "target": "652"}, {"source": "706", "target": "913"}, {"source": "706", "target": "669"}, {"source": "706", "target": "832"}, {"source": "706", "target": "963"}, {"source": "706", "target": "591"}, {"source": "706", "target": "719"}, {"source": "706", "target": "980"}, {"source": "706", "target": "981"}, {"source": "706", "target": "862"}, {"source": "706", "target": "615"}, {"source": "706", "target": "621"}, {"source": "706", "target": "503"}, {"source": "706", "target": "893"}, {"source": "3", "target": "217"}, {"source": "3", "target": "0"}, {"source": "3", "target": "263"}, {"source": "3", "target": "391"}, {"source": "3", "target": "10"}, {"source": "3", "target": "405"}, {"source": "3", "target": "410"}, {"source": "3", "target": "310"}, {"source": "3", "target": "58"}, {"source": "3", "target": "445"}, {"source": "3", "target": "451"}, {"source": "3", "target": "456"}, {"source": "3", "target": "468"}, {"source": "3", "target": "86"}, {"source": "3", "target": "219"}, {"source": "3", "target": "482"}, {"source": "3", "target": "105"}, {"source": "3", "target": "111"}, {"source": "3", "target": "368"}, {"source": "3", "target": "377"}, {"source": "217", "target": "0"}, {"source": "217", "target": "263"}, {"source": "217", "target": "10"}, {"source": "217", "target": "275"}, {"source": "217", "target": "405"}, {"source": "217", "target": "410"}, {"source": "217", "target": "420"}, {"source": "217", "target": "166"}, {"source": "217", "target": "299"}, {"source": "217", "target": "304"}, {"source": "217", "target": "310"}, {"source": "217", "target": "58"}, {"source": "217", "target": "317"}, {"source": "217", "target": "445"}, {"source": "217", "target": "456"}, {"source": "217", "target": "468"}, {"source": "217", "target": "86"}, {"source": "217", "target": "471"}, {"source": "217", "target": "89"}, {"source": "217", "target": "219"}, {"source": "217", "target": "482"}, {"source": "217", "target": "355"}, {"source": "217", "target": "105"}, {"source": "217", "target": "111"}, {"source": "217", "target": "368"}, {"source": "217", "target": "377"}, {"source": "462", "target": "451"}, {"source": "462", "target": "0"}, {"source": "462", "target": "391"}, {"source": "462", "target": "10"}, {"source": "462", "target": "148"}, {"source": "462", "target": "410"}, {"source": "462", "target": "427"}, {"source": "462", "target": "310"}, {"source": "462", "target": "58"}, {"source": "462", "target": "450"}, {"source": "462", "target": "86"}, {"source": "462", "target": "89"}, {"source": "462", "target": "219"}, {"source": "462", "target": "478"}, {"source": "462", "target": "482"}, {"source": "462", "target": "355"}, {"source": "462", "target": "116"}, {"source": "462", "target": "377"}, {"source": "451", "target": "263"}, {"source": "451", "target": "391"}, {"source": "451", "target": "10"}, {"source": "451", "target": "148"}, {"source": "451", "target": "275"}, {"source": "451", "target": "410"}, {"source": "451", "target": "299"}, {"source": "451", "target": "310"}, {"source": "451", "target": "58"}, {"source": "451", "target": "317"}, {"source": "451", "target": "456"}, {"source": "451", "target": "86"}, {"source": "451", "target": "470"}, {"source": "451", "target": "89"}, {"source": "451", "target": "219"}, {"source": "451", "target": "478"}, {"source": "451", "target": "111"}, {"source": "451", "target": "368"}, {"source": "451", "target": "116"}, {"source": "451", "target": "377"}, {"source": "980", "target": "862"}, {"source": "980", "target": "963"}, {"source": "980", "target": "893"}, {"source": "980", "target": "719"}, {"source": "980", "target": "591"}, {"source": "980", "target": "720"}, {"source": "980", "target": "785"}, {"source": "980", "target": "913"}, {"source": "980", "target": "981"}, {"source": "862", "target": "652"}, {"source": "862", "target": "893"}, {"source": "862", "target": "785"}, {"source": "862", "target": "913"}, {"source": "862", "target": "669"}, {"source": "862", "target": "927"}, {"source": "862", "target": "686"}, {"source": "862", "target": "832"}, {"source": "862", "target": "963"}, {"source": "862", "target": "591"}, {"source": "862", "target": "719"}, {"source": "862", "target": "606"}, {"source": "862", "target": "621"}, {"source": "862", "target": "503"}, {"source": "720", "target": "719"}, {"source": "720", "target": "901"}, {"source": "720", "target": "785"}, {"source": "720", "target": "981"}, {"source": "720", "target": "669"}, {"source": "720", "target": "606"}, {"source": "720", "target": "927"}, {"source": "719", "target": "902"}, {"source": "719", "target": "652"}, {"source": "719", "target": "785"}, {"source": "719", "target": "913"}, {"source": "719", "target": "673"}, {"source": "719", "target": "686"}, {"source": "719", "target": "591"}, {"source": "719", "target": "606"}, {"source": "719", "target": "615"}, {"source": "719", "target": "508"}, {"source": "719", "target": "893"}, {"source": "508", "target": "652"}, {"source": "508", "target": "901"}, {"source": "508", "target": "893"}, {"source": "508", "target": "785"}, {"source": "508", "target": "832"}, {"source": "508", "target": "963"}, {"source": "508", "target": "591"}, {"source": "508", "target": "981"}, {"source": "508", "target": "606"}, {"source": "508", "target": "615"}, {"source": "508", "target": "621"}, {"source": "508", "target": "503"}, {"source": "652", "target": "901"}, {"source": "652", "target": "785"}, {"source": "652", "target": "913"}, {"source": "652", "target": "927"}, {"source": "652", "target": "673"}, {"source": "652", "target": "963"}, {"source": "652", "target": "981"}, {"source": "652", "target": "615"}, {"source": "652", "target": "503"}, {"source": "652", "target": "893"}, {"source": "927", "target": "901"}, {"source": "927", "target": "902"}, {"source": "927", "target": "913"}, {"source": "927", "target": "686"}, {"source": "927", "target": "963"}, {"source": "927", "target": "591"}, {"source": "927", "target": "981"}, {"source": "927", "target": "606"}, {"source": "927", "target": "615"}, {"source": "927", "target": "621"}, {"source": "927", "target": "503"}, {"source": "927", "target": "893"}, {"source": "901", "target": "902"}, {"source": "901", "target": "785"}, {"source": "901", "target": "913"}, {"source": "901", "target": "673"}, {"source": "901", "target": "686"}, {"source": "901", "target": "981"}, {"source": "901", "target": "606"}, {"source": "901", "target": "621"}, {"source": "450", "target": "456"}, {"source": "450", "target": "427"}, {"source": "450", "target": "0"}, {"source": "450", "target": "263"}, {"source": "450", "target": "405"}, {"source": "450", "target": "410"}, {"source": "450", "target": "413"}, {"source": "450", "target": "426"}, {"source": "450", "target": "304"}, {"source": "450", "target": "310"}, {"source": "450", "target": "445"}, {"source": "450", "target": "86"}, {"source": "450", "target": "470"}, {"source": "450", "target": "89"}, {"source": "450", "target": "478"}, {"source": "450", "target": "482"}, {"source": "450", "target": "105"}, {"source": "450", "target": "368"}, {"source": "450", "target": "116"}, {"source": "456", "target": "263"}, {"source": "456", "target": "148"}, {"source": "456", "target": "405"}, {"source": "456", "target": "410"}, {"source": "456", "target": "413"}, {"source": "456", "target": "420"}, {"source": "456", "target": "426"}, {"source": "456", "target": "299"}, {"source": "456", "target": "304"}, {"source": "456", "target": "310"}, {"source": "456", "target": "58"}, {"source": "456", "target": "468"}, {"source": "456", "target": "86"}, {"source": "456", "target": "471"}, {"source": "456", "target": "219"}, {"source": "456", "target": "478"}, {"source": "456", "target": "111"}, {"source": "456", "target": "116"}, {"source": "105", "target": "420"}, {"source": "105", "target": "405"}, {"source": "105", "target": "0"}, {"source": "105", "target": "263"}, {"source": "105", "target": "391"}, {"source": "105", "target": "10"}, {"source": "105", "target": "275"}, {"source": "105", "target": "148"}, {"source": "105", "target": "410"}, {"source": "105", "target": "304"}, {"source": "105", "target": "58"}, {"source": "105", "target": "468"}, {"source": "105", "target": "470"}, {"source": "105", "target": "219"}, {"source": "105", "target": "355"}, {"source": "105", "target": "368"}, {"source": "105", "target": "116"}, {"source": "105", "target": "377"}, {"source": "420", "target": "0"}, {"source": "420", "target": "391"}, {"source": "420", "target": "148"}, {"source": "420", "target": "405"}, {"source": "420", "target": "166"}, {"source": "420", "target": "427"}, {"source": "420", "target": "304"}, {"source": "420", "target": "58"}, {"source": "420", "target": "445"}, {"source": "420", "target": "468"}, {"source": "420", "target": "470"}, {"source": "420", "target": "89"}, {"source": "420", "target": "478"}, {"source": "420", "target": "355"}, {"source": "420", "target": "111"}, {"source": "420", "target": "377"}, {"source": "111", "target": "355"}, {"source": "111", "target": "0"}, {"source": "111", "target": "263"}, {"source": "111", "target": "10"}, {"source": "111", "target": "405"}, {"source": "111", "target": "410"}, {"source": "111", "target": "166"}, {"source": "111", "target": "426"}, {"source": "111", "target": "427"}, {"source": "111", "target": "468"}, {"source": "111", "target": "86"}, {"source": "111", "target": "89"}, {"source": "111", "target": "219"}, {"source": "111", "target": "116"}, {"source": "111", "target": "377"}, {"source": "355", "target": "0"}, {"source": "355", "target": "391"}, {"source": "355", "target": "10"}, {"source": "355", "target": "148"}, {"source": "355", "target": "275"}, {"source": "355", "target": "410"}, {"source": "355", "target": "413"}, {"source": "355", "target": "166"}, {"source": "355", "target": "426"}, {"source": "355", "target": "299"}, {"source": "355", "target": "427"}, {"source": "355", "target": "304"}, {"source": "355", "target": "58"}, {"source": "355", "target": "317"}, {"source": "355", "target": "86"}, {"source": "355", "target": "470"}, {"source": "355", "target": "89"}, {"source": "355", "target": "478"}, {"source": "355", "target": "368"}, {"source": "669", "target": "981"}, {"source": "669", "target": "902"}, {"source": "669", "target": "785"}, {"source": "669", "target": "673"}, {"source": "669", "target": "832"}, {"source": "669", "target": "963"}, {"source": "669", "target": "591"}, {"source": "669", "target": "606"}, {"source": "981", "target": "913"}, {"source": "981", "target": "673"}, {"source": "981", "target": "832"}, {"source": "981", "target": "615"}, {"source": "981", "target": "621"}, {"source": "913", "target": "785"}, {"source": "913", "target": "673"}, {"source": "913", "target": "832"}, {"source": "913", "target": "963"}, {"source": "913", "target": "591"}, {"source": "913", "target": "503"}, {"source": "913", "target": "893"}, {"source": "785", "target": "686"}, {"source": "785", "target": "673"}, {"source": "785", "target": "832"}, {"source": "785", "target": "963"}, {"source": "785", "target": "591"}, {"source": "785", "target": "606"}, {"source": "785", "target": "621"}, {"source": "785", "target": "893"}, {"source": "377", "target": "89"}, {"source": "377", "target": "391"}, {"source": "377", "target": "405"}, {"source": "377", "target": "410"}, {"source": "377", "target": "310"}, {"source": "377", "target": "317"}, {"source": "377", "target": "445"}, {"source": "377", "target": "86"}, {"source": "377", "target": "219"}, {"source": "377", "target": "368"}, {"source": "377", "target": "116"}, {"source": "89", "target": "263"}, {"source": "89", "target": "391"}, {"source": "89", "target": "10"}, {"source": "89", "target": "148"}, {"source": "89", "target": "410"}, {"source": "89", "target": "166"}, {"source": "89", "target": "426"}, {"source": "89", "target": "299"}, {"source": "89", "target": "304"}, {"source": "89", "target": "445"}, {"source": "89", "target": "468"}, {"source": "89", "target": "86"}, {"source": "89", "target": "470"}, {"source": "89", "target": "219"}, {"source": "89", "target": "478"}, {"source": "89", "target": "482"}, {"source": "89", "target": "368"}, {"source": "621", "target": "615"}, {"source": "621", "target": "902"}, {"source": "621", "target": "591"}, {"source": "621", "target": "503"}, {"source": "615", "target": "902"}, {"source": "615", "target": "832"}, {"source": "615", "target": "963"}, {"source": "615", "target": "591"}, {"source": "615", "target": "606"}, {"source": "615", "target": "893"}, {"source": "503", "target": "963"}, {"source": "503", "target": "902"}, {"source": "503", "target": "893"}, {"source": "503", "target": "686"}, {"source": "503", "target": "591"}, {"source": "963", "target": "902"}, {"source": "963", "target": "893"}, {"source": "963", "target": "673"}, {"source": "963", "target": "591"}, {"source": "405", "target": "10"}, {"source": "405", "target": "275"}, {"source": "405", "target": "426"}, {"source": "405", "target": "299"}, {"source": "405", "target": "427"}, {"source": "405", "target": "317"}, {"source": "405", "target": "445"}, {"source": "405", "target": "468"}, {"source": "405", "target": "86"}, {"source": "405", "target": "470"}, {"source": "405", "target": "471"}, {"source": "405", "target": "478"}, {"source": "405", "target": "482"}, {"source": "405", "target": "116"}, {"source": "686", "target": "673"}, {"source": "686", "target": "902"}, {"source": "686", "target": "606"}, {"source": "426", "target": "391"}, {"source": "426", "target": "10"}, {"source": "426", "target": "410"}, {"source": "426", "target": "413"}, {"source": "426", "target": "166"}, {"source": "426", "target": "299"}, {"source": "426", "target": "427"}, {"source": "426", "target": "310"}, {"source": "426", "target": "317"}, {"source": "426", "target": "445"}, {"source": "426", "target": "468"}, {"source": "426", "target": "86"}, {"source": "426", "target": "471"}, {"source": "426", "target": "219"}, {"source": "426", "target": "482"}, {"source": "10", "target": "445"}, {"source": "10", "target": "263"}, {"source": "10", "target": "148"}, {"source": "10", "target": "166"}, {"source": "10", "target": "310"}, {"source": "10", "target": "86"}, {"source": "10", "target": "471"}, {"source": "10", "target": "478"}, {"source": "10", "target": "368"}, {"source": "10", "target": "116"}, {"source": "445", "target": "263"}, {"source": "445", "target": "391"}, {"source": "445", "target": "410"}, {"source": "445", "target": "166"}, {"source": "445", "target": "299"}, {"source": "445", "target": "304"}, {"source": "445", "target": "86"}, {"source": "445", "target": "470"}, {"source": "445", "target": "219"}, {"source": "445", "target": "482"}, {"source": "445", "target": "368"}, {"source": "58", "target": "299"}, {"source": "58", "target": "0"}, {"source": "58", "target": "263"}, {"source": "58", "target": "275"}, {"source": "58", "target": "410"}, {"source": "58", "target": "413"}, {"source": "58", "target": "310"}, {"source": "58", "target": "468"}, {"source": "58", "target": "86"}, {"source": "58", "target": "471"}, {"source": "58", "target": "219"}, {"source": "58", "target": "478"}, {"source": "58", "target": "482"}, {"source": "58", "target": "116"}, {"source": "299", "target": "0"}, {"source": "299", "target": "166"}, {"source": "299", "target": "468"}, {"source": "299", "target": "471"}, {"source": "299", "target": "478"}, {"source": "299", "target": "368"}, {"source": "299", "target": "116"}, {"source": "263", "target": "317"}, {"source": "263", "target": "0"}, {"source": "263", "target": "391"}, {"source": "263", "target": "148"}, {"source": "263", "target": "410"}, {"source": "263", "target": "413"}, {"source": "263", "target": "166"}, {"source": "263", "target": "427"}, {"source": "263", "target": "304"}, {"source": "263", "target": "86"}, {"source": "263", "target": "478"}, {"source": "263", "target": "482"}, {"source": "263", "target": "116"}, {"source": "317", "target": "0"}, {"source": "317", "target": "391"}, {"source": "317", "target": "148"}, {"source": "317", "target": "275"}, {"source": "317", "target": "410"}, {"source": "317", "target": "413"}, {"source": "317", "target": "166"}, {"source": "317", "target": "427"}, {"source": "317", "target": "310"}, {"source": "317", "target": "86"}, {"source": "317", "target": "471"}, {"source": "317", "target": "219"}, {"source": "317", "target": "478"}, {"source": "317", "target": "368"}, {"source": "317", "target": "116"}, {"source": "482", "target": "410"}, {"source": "482", "target": "0"}, {"source": "482", "target": "391"}, {"source": "482", "target": "275"}, {"source": "482", "target": "413"}, {"source": "482", "target": "427"}, {"source": "482", "target": "304"}, {"source": "482", "target": "468"}, {"source": "482", "target": "86"}, {"source": "482", "target": "471"}, {"source": "482", "target": "219"}, {"source": "482", "target": "478"}, {"source": "482", "target": "368"}, {"source": "482", "target": "116"}, {"source": "410", "target": "148"}, {"source": "410", "target": "304"}, {"source": "410", "target": "310"}, {"source": "410", "target": "468"}, {"source": "410", "target": "471"}, {"source": "410", "target": "219"}, {"source": "410", "target": "368"}, {"source": "410", "target": "116"}, {"source": "591", "target": "606"}, {"source": "591", "target": "902"}, {"source": "591", "target": "832"}, {"source": "606", "target": "673"}, {"source": "832", "target": "893"}, {"source": "832", "target": "902"}, {"source": "893", "target": "673"}, {"source": "427", "target": "0"}, {"source": "427", "target": "275"}, {"source": "427", "target": "148"}, {"source": "427", "target": "413"}, {"source": "427", "target": "166"}, {"source": "427", "target": "304"}, {"source": "427", "target": "310"}, {"source": "427", "target": "468"}, {"source": "427", "target": "470"}, {"source": "427", "target": "471"}, {"source": "427", "target": "219"}, {"source": "427", "target": "478"}, {"source": "427", "target": "116"}, {"source": "902", "target": "673"}, {"source": "275", "target": "391"}, {"source": "275", "target": "0"}, {"source": "275", "target": "148"}, {"source": "275", "target": "166"}, {"source": "275", "target": "304"}, {"source": "275", "target": "470"}, {"source": "275", "target": "471"}, {"source": "275", "target": "478"}, {"source": "391", "target": "0"}, {"source": "391", "target": "304"}, {"source": "391", "target": "219"}, {"source": "391", "target": "478"}, {"source": "391", "target": "116"}, {"source": "166", "target": "304"}, {"source": "166", "target": "148"}, {"source": "166", "target": "413"}, {"source": "166", "target": "310"}, {"source": "166", "target": "468"}, {"source": "166", "target": "86"}, {"source": "166", "target": "470"}, {"source": "166", "target": "368"}, {"source": "304", "target": "310"}, {"source": "304", "target": "468"}, {"source": "304", "target": "86"}, {"source": "304", "target": "471"}, {"source": "304", "target": "478"}, {"source": "304", "target": "368"}, {"source": "304", "target": "116"}, {"source": "148", "target": "478"}, {"source": "148", "target": "0"}, {"source": "148", "target": "86"}, {"source": "148", "target": "470"}, {"source": "148", "target": "471"}, {"source": "148", "target": "116"}, {"source": "478", "target": "0"}, {"source": "478", "target": "413"}, {"source": "478", "target": "310"}, {"source": "478", "target": "468"}, {"source": "478", "target": "86"}, {"source": "478", "target": "470"}, {"source": "478", "target": "471"}, {"source": "470", "target": "413"}, {"source": "470", "target": "0"}, {"source": "470", "target": "310"}, {"source": "470", "target": "468"}, {"source": "470", "target": "86"}, {"source": "470", "target": "471"}, {"source": "470", "target": "116"}, {"source": "413", "target": "468"}, {"source": "413", "target": "86"}, {"source": "413", "target": "471"}, {"source": "413", "target": "368"}, {"source": "116", "target": "471"}, {"source": "116", "target": "0"}, {"source": "116", "target": "310"}, {"source": "116", "target": "468"}, {"source": "116", "target": "219"}, {"source": "116", "target": "368"}, {"source": "471", "target": "0"}, {"source": "471", "target": "310"}, {"source": "471", "target": "86"}, {"source": "86", "target": "368"}, {"source": "86", "target": "0"}, {"source": "86", "target": "310"}, {"source": "368", "target": "310"}, {"source": "368", "target": "468"}, {"source": "368", "target": "219"}, {"source": "219", "target": "468"}, {"source": "219", "target": "0"}, {"source": "468", "target": "0"}, {"source": "468", "target": "310"}, {"source": "0", "target": "310"}]}