{"nodes": ["0", "6", "14", "20", "21", "26", "27", "30", "36", "39", "44", "51", "55", "56", "58", "60", "64", "75", "95", "96", "98", "102", "107", "108", "110", "117", "118", "119", "122", "135", "137", "145", "148", "152", "153", "157", "158", "160", "164", "166", "171", "179", "182", "183", "185", "193", "195", "199", "201", "204", "207", "212", "215", "220", "222", "234", "240", "242", "243", "244", "249", "255", "256", "258", "259", "266", "269", "273", "279", "292", "296", "298", "299", "302", "305", "312", "315", "325", "326", "327", "332", "334", "338", "340", "342", "347", "359", "360", "361", "372", "374", "375", "384", "386", "387", "388", "389", "390", "396", "405", "407", "408", "412", "413", "415", "416", "421", "425", "426", "429", "434", "435", "436", "439", "440", "441", "442", "451", "453", "461", "463", "471", "472", "475", "480", "481", "482", "485", "487", "495", "496", "497", "499", "500", "505", "507", "511", "527", "529", "536", "539", "540", "541", "544", "547", "554", "555", "558", "559", "561", "567", "573", "574", "576", "581", "583", "584", "599", "602", "605", "615", "616", "622", "624", "625", "626", "633", "635", "661", "667", "671", "672", "673", "677", "678", "679", "683", "688", "689", "690", "691", "696", "697", "701", "714", "717", "718", "719", "726", "730", "736", "737", "739", "744", "745", "750", "755", "757", "766", "773", "777", "788", "790", "797", "798", "799", "801", "810", "813", "821", "823", "833", "835", "838", "842", "843", "848", "863", "880", "881", "883", "886", "888", "893", "898", "901", "902", "904", "906", "912", "929", "932", "935", "937", "938", "941", "952", "953", "954", "957", "961", "964", "969", "979", "980", "983", "986", "989", "995", "997", "998"], "edges": [{"source": "616", "target": "813"}, {"source": "929", "target": "980"}, {"source": "332", "target": "412"}, {"source": "332", "target": "312"}, {"source": "412", "target": "312"}, {"source": "842", "target": "938"}, {"source": "20", "target": "269"}, {"source": "269", "target": "298"}, {"source": "201", "target": "234"}, {"source": "234", "target": "405"}, {"source": "298", "target": "421"}, {"source": "298", "target": "482"}, {"source": "299", "target": "425"}, {"source": "102", "target": "453"}, {"source": "453", "target": "158"}, {"source": "266", "target": "384"}, {"source": "266", "target": "396"}, {"source": "266", "target": "39"}, {"source": "153", "target": "416"}, {"source": "153", "target": "487"}, {"source": "340", "target": "374"}, {"source": "766", "target": "773"}, {"source": "429", "target": "434"}, {"source": "434", "target": "441"}, {"source": "334", "target": "413"}, {"source": "108", "target": "215"}, {"source": "215", "target": "388"}, {"source": "122", "target": "164"}, {"source": "64", "target": "387"}, {"source": "64", "target": "27"}, {"source": "701", "target": "953"}, {"source": "119", "target": "407"}, {"source": "697", "target": "881"}, {"source": "14", "target": "315"}, {"source": "544", "target": "750"}, {"source": "797", "target": "810"}, {"source": "6", "target": "160"}, {"source": "157", "target": "463"}, {"source": "157", "target": "199"}, {"source": "540", "target": "541"}, {"source": "678", "target": "937"}, {"source": "678", "target": "714"}, {"source": "937", "target": "633"}, {"source": "888", "target": "961"}, {"source": "744", "target": "902"}, {"source": "744", "target": "757"}, {"source": "777", "target": "799"}, {"source": "539", "target": "788"}, {"source": "539", "target": "690"}, {"source": "440", "target": "471"}, {"source": "273", "target": "496"}, {"source": "559", "target": "964"}, {"source": "44", "target": "207"}, {"source": "696", "target": "997"}, {"source": "554", "target": "717"}, {"source": "51", "target": "451"}, {"source": "51", "target": "259"}, {"source": "843", "target": "998"}, {"source": "671", "target": "835"}, {"source": "835", "target": "952"}, {"source": "677", "target": "679"}, {"source": "745", "target": "880"}, {"source": "388", "target": "152"}, {"source": "55", "target": "255"}, {"source": "55", "target": "347"}, {"source": "555", "target": "661"}, {"source": "547", "target": "615"}, {"source": "730", "target": "954"}, {"source": "183", "target": "292"}, {"source": "688", "target": "957"}, {"source": "624", "target": "673"}, {"source": "691", "target": "983"}, {"source": "691", "target": "969"}, {"source": "152", "target": "166"}, {"source": "279", "target": "495"}, {"source": "536", "target": "995"}, {"source": "60", "target": "249"}, {"source": "326", "target": "439"}, {"source": "96", "target": "390"}, {"source": "118", "target": "372"}, {"source": "244", "target": "426"}, {"source": "107", "target": "117"}, {"source": "56", "target": "95"}, {"source": "507", "target": "932"}, {"source": "507", "target": "500"}, {"source": "726", "target": "821"}, {"source": "667", "target": "689"}, {"source": "529", "target": "912"}, {"source": "584", "target": "989"}, {"source": "0", "target": "58"}, {"source": "58", "target": "193"}, {"source": "148", "target": "435"}, {"source": "148", "target": "461"}, {"source": "599", "target": "737"}, {"source": "527", "target": "801"}, {"source": "576", "target": "838"}, {"source": "242", "target": "415"}, {"source": "573", "target": "605"}, {"source": "98", "target": "110"}, {"source": "635", "target": "898"}, {"source": "561", "target": "935"}, {"source": "935", "target": "719"}, {"source": "442", "target": "480"}, {"source": "480", "target": "327"}, {"source": "325", "target": "408"}, {"source": "886", "target": "941"}, {"source": "558", "target": "683"}, {"source": "21", "target": "204"}, {"source": "137", "target": "240"}, {"source": "240", "target": "171"}, {"source": "497", "target": "499"}, {"source": "500", "target": "511"}, {"source": "179", "target": "258"}, {"source": "36", "target": "243"}, {"source": "220", "target": "481"}, {"source": "342", "target": "472"}, {"source": "75", "target": "338"}, {"source": "622", "target": "901"}, {"source": "602", "target": "672"}, {"source": "359", "target": "475"}, {"source": "182", "target": "222"}, {"source": "212", "target": "256"}, {"source": "135", "target": "485"}, {"source": "302", "target": "389"}, {"source": "626", "target": "798"}, {"source": "626", "target": "883"}, {"source": "26", "target": "30"}, {"source": "718", "target": "790"}, {"source": "863", "target": "979"}, {"source": "305", "target": "375"}, {"source": "195", "target": "360"}, {"source": "185", "target": "386"}, {"source": "736", "target": "848"}, {"source": "833", "target": "893"}, {"source": "581", "target": "906"}, {"source": "505", "target": "583"}, {"source": "567", "target": "625"}, {"source": "145", "target": "436"}, {"source": "904", "target": "986"}, {"source": "574", "target": "823"}, {"source": "739", "target": "755"}, {"source": "296", "target": "361"}]}