{"nodes": [{"communitynum": 0, "value": 114}, {"communitynum": 1, "value": 198}, {"communitynum": 2, "value": 79}, {"communitynum": 3, "value": 100}, {"communitynum": 4, "value": 85}, {"communitynum": 5, "value": 177}, {"communitynum": 6, "value": 82}, {"communitynum": 7, "value": 137}, {"communitynum": 8, "value": 57}, {"communitynum": 9, "value": 74}, {"communitynum": 10, "value": 84}, {"communitynum": 11, "value": 59}, {"communitynum": 12, "value": 40}, {"communitynum": 13, "value": 2}, {"communitynum": 14, "value": 2}, {"communitynum": 15, "value": 3}, {"communitynum": 16, "value": 2}, {"communitynum": 17, "value": 2}, {"communitynum": 18, "value": 3}, {"communitynum": 19, "value": 2}, {"communitynum": 20, "value": 3}, {"communitynum": 21, "value": 2}, {"communitynum": 22, "value": 2}, {"communitynum": 23, "value": 2}, {"communitynum": 24, "value": 3}, {"communitynum": 25, "value": 2}, {"communitynum": 26, "value": 4}, {"communitynum": 27, "value": 2}, {"communitynum": 28, "value": 2}, {"communitynum": 29, "value": 4}, {"communitynum": 30, "value": 4}, {"communitynum": 31, "value": 2}, {"communitynum": 32, "value": 2}, {"communitynum": 33, "value": 1}, {"communitynum": 34, "value": 1}, {"communitynum": 35, "value": 1}, {"communitynum": 36, "value": 1}, {"communitynum": 37, "value": 1}, {"communitynum": 38, "value": 1}, {"communitynum": 39, "value": 1}, {"communitynum": 40, "value": 1}, {"communitynum": 41, "value": 1}, {"communitynum": 42, "value": 1}, {"communitynum": 43, "value": 1}, {"communitynum": 44, "value": 1}, {"communitynum": 45, "value": 1}, {"communitynum": 46, "value": 1}, {"communitynum": 47, "value": 1}, {"communitynum": 48, "value": 1}, {"communitynum": 49, "value": 1}, {"communitynum": 50, "value": 1}, {"communitynum": 51, "value": 1}, {"communitynum": 52, "value": 1}, {"communitynum": 53, "value": 1}, {"communitynum": 54, "value": 1}, {"communitynum": 55, "value": 1}, {"communitynum": 56, "value": 1}, {"communitynum": 57, "value": 1}, {"communitynum": 58, "value": 1}, {"communitynum": 59, "value": 1}, {"communitynum": 60, "value": 1}, {"communitynum": 61, "value": 1}, {"communitynum": 62, "value": 1}, {"communitynum": 63, "value": 1}, {"communitynum": 64, "value": 1}, {"communitynum": 65, "value": 1}, {"communitynum": 66, "value": 1}, {"communitynum": 67, "value": 1}, {"communitynum": 68, "value": 1}, {"communitynum": 69, "value": 1}, {"communitynum": 70, "value": 1}, {"communitynum": 71, "value": 1}, {"communitynum": 72, "value": 1}, {"communitynum": 73, "value": 1}, {"communitynum": 74, "value": 1}, {"communitynum": 75, "value": 1}, {"communitynum": 76, "value": 1}, {"communitynum": 77, "value": 1}, {"communitynum": 78, "value": 1}, {"communitynum": 79, "value": 1}, {"communitynum": 80, "value": 1}, {"communitynum": 81, "value": 1}, {"communitynum": 82, "value": 1}, {"communitynum": 83, "value": 1}, {"communitynum": 84, "value": 1}, {"communitynum": 85, "value": 1}, {"communitynum": 86, "value": 1}, {"communitynum": 87, "value": 1}, {"communitynum": 88, "value": 1}, {"communitynum": 89, "value": 1}, {"communitynum": 90, "value": 1}, {"communitynum": 91, "value": 1}, {"communitynum": 92, "value": 1}, {"communitynum": 93, "value": 1}, {"communitynum": 94, "value": 1}, {"communitynum": 95, "value": 1}, {"communitynum": 96, "value": 1}, {"communitynum": 97, "value": 1}, {"communitynum": 98, "value": 1}, {"communitynum": 99, "value": 1}, {"communitynum": 100, "value": 1}, {"communitynum": 101, "value": 1}, {"communitynum": 102, "value": 1}, {"communitynum": 103, "value": 1}, {"communitynum": 104, "value": 1}, {"communitynum": 105, "value": 1}, {"communitynum": 106, "value": 1}, {"communitynum": 107, "value": 1}, {"communitynum": 108, "value": 1}, {"communitynum": 109, "value": 1}, {"communitynum": 110, "value": 1}, {"communitynum": 111, "value": 1}, {"communitynum": 112, "value": 1}, {"communitynum": 113, "value": 1}, {"communitynum": 114, "value": 1}, {"communitynum": 115, "value": 1}, {"communitynum": 116, "value": 1}, {"communitynum": 117, "value": 1}, {"communitynum": 118, "value": 1}, {"communitynum": 119, "value": 1}, {"communitynum": 120, "value": 1}, {"communitynum": 121, "value": 1}, {"communitynum": 122, "value": 1}, {"communitynum": 123, "value": 1}, {"communitynum": 124, "value": 1}, {"communitynum": 125, "value": 1}, {"communitynum": 126, "value": 1}, {"communitynum": 127, "value": 1}, {"communitynum": 128, "value": 1}, {"communitynum": 129, "value": 1}, {"communitynum": 130, "value": 1}, {"communitynum": 131, "value": 1}, {"communitynum": 132, "value": 1}, {"communitynum": 133, "value": 1}, {"communitynum": 134, "value": 1}, {"communitynum": 135, "value": 1}, {"communitynum": 136, "value": 1}, {"communitynum": 137, "value": 1}, {"communitynum": 138, "value": 1}, {"communitynum": 139, "value": 1}, {"communitynum": 140, "value": 1}, {"communitynum": 141, "value": 1}, {"communitynum": 142, "value": 1}, {"communitynum": 143, "value": 1}, {"communitynum": 144, "value": 1}, {"communitynum": 145, "value": 1}, {"communitynum": 146, "value": 1}, {"communitynum": 147, "value": 1}, {"communitynum": 148, "value": 1}, {"communitynum": 149, "value": 1}, {"communitynum": 150, "value": 1}, {"communitynum": 151, "value": 1}, {"communitynum": 152, "value": 1}, {"communitynum": 153, "value": 1}, {"communitynum": 154, "value": 1}, {"communitynum": 155, "value": 1}, {"communitynum": 156, "value": 1}, {"communitynum": 157, "value": 1}, {"communitynum": 158, "value": 1}, {"communitynum": 159, "value": 1}, {"communitynum": 160, "value": 1}, {"communitynum": 161, "value": 1}, {"communitynum": 162, "value": 1}, {"communitynum": 163, "value": 1}, {"communitynum": 164, "value": 1}, {"communitynum": 165, "value": 1}, {"communitynum": 166, "value": 1}, {"communitynum": 167, "value": 1}, {"communitynum": 168, "value": 1}, {"communitynum": 169, "value": 1}, {"communitynum": 170, "value": 1}, {"communitynum": 171, "value": 1}, {"communitynum": 172, "value": 1}, {"communitynum": 173, "value": 1}, {"communitynum": 174, "value": 1}, {"communitynum": 175, "value": 1}, {"communitynum": 176, "value": 1}, {"communitynum": 177, "value": 1}, {"communitynum": 178, "value": 1}, {"communitynum": 179, "value": 1}, {"communitynum": 180, "value": 1}, {"communitynum": 181, "value": 1}, {"communitynum": 182, "value": 1}, {"communitynum": 183, "value": 1}, {"communitynum": 184, "value": 1}, {"communitynum": 185, "value": 1}, {"communitynum": 186, "value": 1}, {"communitynum": 187, "value": 1}, {"communitynum": 188, "value": 1}, {"communitynum": 189, "value": 1}, {"communitynum": 190, "value": 1}, {"communitynum": 191, "value": 1}, {"communitynum": 192, "value": 1}, {"communitynum": 193, "value": 1}, {"communitynum": 194, "value": 1}, {"communitynum": 195, "value": 1}, {"communitynum": 196, "value": 1}, {"communitynum": 197, "value": 1}, {"communitynum": 198, "value": 1}, {"communitynum": 199, "value": 1}, {"communitynum": 200, "value": 1}, {"communitynum": 201, "value": 1}, {"communitynum": 202, "value": 1}, {"communitynum": 203, "value": 1}, {"communitynum": 204, "value": 1}, {"communitynum": 205, "value": 1}, {"communitynum": 206, "value": 1}, {"communitynum": 207, "value": 1}, {"communitynum": 208, "value": 1}, {"communitynum": 209, "value": 1}, {"communitynum": 210, "value": 1}, {"communitynum": 211, "value": 1}, {"communitynum": 212, "value": 1}, {"communitynum": 213, "value": 1}, {"communitynum": 214, "value": 1}, {"communitynum": 215, "value": 1}, {"communitynum": 216, "value": 1}, {"communitynum": 217, "value": 1}, {"communitynum": 218, "value": 1}, {"communitynum": 219, "value": 1}, {"communitynum": 220, "value": 1}, {"communitynum": 221, "value": 1}, {"communitynum": 222, "value": 1}, {"communitynum": 223, "value": 1}, {"communitynum": 224, "value": 1}, {"communitynum": 225, "value": 1}, {"communitynum": 226, "value": 1}, {"communitynum": 227, "value": 1}, {"communitynum": 228, "value": 1}, {"communitynum": 229, "value": 1}, {"communitynum": 230, "value": 1}, {"communitynum": 231, "value": 1}, {"communitynum": 232, "value": 1}, {"communitynum": 233, "value": 1}, {"communitynum": 234, "value": 1}, {"communitynum": 235, "value": 1}, {"communitynum": 236, "value": 1}, {"communitynum": 237, "value": 1}, {"communitynum": 238, "value": 1}, {"communitynum": 239, "value": 1}, {"communitynum": 240, "value": 1}, {"communitynum": 241, "value": 1}, {"communitynum": 242, "value": 1}, {"communitynum": 243, "value": 1}, {"communitynum": 244, "value": 1}, {"communitynum": 245, "value": 1}, {"communitynum": 246, "value": 1}, {"communitynum": 247, "value": 1}, {"communitynum": 248, "value": 1}, {"communitynum": 249, "value": 1}, {"communitynum": 250, "value": 1}, {"communitynum": 251, "value": 1}, {"communitynum": 252, "value": 1}, {"communitynum": 253, "value": 1}, {"communitynum": 254, "value": 1}, {"communitynum": 255, "value": 1}, {"communitynum": 256, "value": 1}, {"communitynum": 257, "value": 1}, {"communitynum": 258, "value": 1}, {"communitynum": 259, "value": 1}, {"communitynum": 260, "value": 1}, {"communitynum": 261, "value": 1}, {"communitynum": 262, "value": 1}, {"communitynum": 263, "value": 1}, {"communitynum": 264, "value": 1}, {"communitynum": 265, "value": 1}, {"communitynum": 266, "value": 1}, {"communitynum": 267, "value": 1}, {"communitynum": 268, "value": 1}, {"communitynum": 269, "value": 1}, {"communitynum": 270, "value": 1}, {"communitynum": 271, "value": 1}, {"communitynum": 272, "value": 1}, {"communitynum": 273, "value": 1}, {"communitynum": 274, "value": 1}, {"communitynum": 275, "value": 1}, {"communitynum": 276, "value": 1}, {"communitynum": 277, "value": 1}, {"communitynum": 278, "value": 1}, {"communitynum": 279, "value": 1}, {"communitynum": 280, "value": 1}, {"communitynum": 281, "value": 1}, {"communitynum": 282, "value": 1}, {"communitynum": 283, "value": 1}, {"communitynum": 284, "value": 1}, {"communitynum": 285, "value": 1}, {"communitynum": 286, "value": 1}, {"communitynum": 287, "value": 1}, {"communitynum": 288, "value": 1}, {"communitynum": 289, "value": 1}, {"communitynum": 290, "value": 1}, {"communitynum": 291, "value": 1}, {"communitynum": 292, "value": 1}, {"communitynum": 293, "value": 1}, {"communitynum": 294, "value": 1}, {"communitynum": 295, "value": 1}, {"communitynum": 296, "value": 1}, {"communitynum": 297, "value": 1}, {"communitynum": 298, "value": 1}, {"communitynum": 299, "value": 1}, {"communitynum": 300, "value": 1}, {"communitynum": 301, "value": 1}, {"communitynum": 302, "value": 1}, {"communitynum": 303, "value": 1}, {"communitynum": 304, "value": 1}, {"communitynum": 305, "value": 1}, {"communitynum": 306, "value": 1}, {"communitynum": 307, "value": 1}, {"communitynum": 308, "value": 1}, {"communitynum": 309, "value": 1}, {"communitynum": 310, "value": 1}, {"communitynum": 311, "value": 1}, {"communitynum": 312, "value": 1}, {"communitynum": 313, "value": 1}, {"communitynum": 314, "value": 1}, {"communitynum": 315, "value": 1}, {"communitynum": 316, "value": 1}, {"communitynum": 317, "value": 1}, {"communitynum": 318, "value": 1}, {"communitynum": 319, "value": 1}, {"communitynum": 320, "value": 1}, {"communitynum": 321, "value": 1}, {"communitynum": 322, "value": 1}, {"communitynum": 323, "value": 1}, {"communitynum": 324, "value": 1}, {"communitynum": 325, "value": 1}, {"communitynum": 326, "value": 1}, {"communitynum": 327, "value": 1}, {"communitynum": 328, "value": 1}, {"communitynum": 329, "value": 1}, {"communitynum": 330, "value": 1}, {"communitynum": 331, "value": 1}, {"communitynum": 332, "value": 1}, {"communitynum": 333, "value": 1}, {"communitynum": 334, "value": 1}, {"communitynum": 335, "value": 1}, {"communitynum": 336, "value": 1}, {"communitynum": 337, "value": 1}, {"communitynum": 338, "value": 1}, {"communitynum": 339, "value": 1}, {"communitynum": 340, "value": 1}, {"communitynum": 341, "value": 1}, {"communitynum": 342, "value": 1}, {"communitynum": 343, "value": 1}, {"communitynum": 344, "value": 1}, {"communitynum": 345, "value": 1}, {"communitynum": 346, "value": 1}, {"communitynum": 347, "value": 1}, {"communitynum": 348, "value": 1}, {"communitynum": 349, "value": 1}, {"communitynum": 350, "value": 1}, {"communitynum": 351, "value": 1}, {"communitynum": 352, "value": 1}, {"communitynum": 353, "value": 1}, {"communitynum": 354, "value": 1}, {"communitynum": 355, "value": 1}, {"communitynum": 356, "value": 1}, {"communitynum": 357, "value": 1}, {"communitynum": 358, "value": 1}, {"communitynum": 359, "value": 1}, {"communitynum": 360, "value": 1}, {"communitynum": 361, "value": 1}, {"communitynum": 362, "value": 1}, {"communitynum": 363, "value": 1}, {"communitynum": 364, "value": 1}, {"communitynum": 365, "value": 1}, {"communitynum": 366, "value": 1}, {"communitynum": 367, "value": 1}, {"communitynum": 368, "value": 1}, {"communitynum": 369, "value": 1}, {"communitynum": 370, "value": 1}, {"communitynum": 371, "value": 1}, {"communitynum": 372, "value": 1}, {"communitynum": 373, "value": 1}, {"communitynum": 374, "value": 1}, {"communitynum": 375, "value": 1}, {"communitynum": 376, "value": 1}, {"communitynum": 377, "value": 1}, {"communitynum": 378, "value": 1}, {"communitynum": 379, "value": 1}, {"communitynum": 380, "value": 1}, {"communitynum": 381, "value": 1}, {"communitynum": 382, "value": 1}, {"communitynum": 383, "value": 1}, {"communitynum": 384, "value": 1}, {"communitynum": 385, "value": 1}, {"communitynum": 386, "value": 1}, {"communitynum": 387, "value": 1}, {"communitynum": 388, "value": 1}, {"communitynum": 389, "value": 1}, {"communitynum": 390, "value": 1}, {"communitynum": 391, "value": 1}, {"communitynum": 392, "value": 1}, {"communitynum": 393, "value": 1}, {"communitynum": 394, "value": 1}, {"communitynum": 395, "value": 1}, {"communitynum": 396, "value": 1}, {"communitynum": 397, "value": 1}, {"communitynum": 398, "value": 1}, {"communitynum": 399, "value": 1}, {"communitynum": 400, "value": 1}, {"communitynum": 401, "value": 1}, {"communitynum": 402, "value": 1}, {"communitynum": 403, "value": 1}, {"communitynum": 404, "value": 1}, {"communitynum": 405, "value": 1}, {"communitynum": 406, "value": 1}, {"communitynum": 407, "value": 1}, {"communitynum": 408, "value": 1}, {"communitynum": 409, "value": 1}, {"communitynum": 410, "value": 1}, {"communitynum": 411, "value": 1}, {"communitynum": 412, "value": 1}, {"communitynum": 413, "value": 1}, {"communitynum": 414, "value": 1}, {"communitynum": 415, "value": 1}, {"communitynum": 416, "value": 1}, {"communitynum": 417, "value": 1}, {"communitynum": 418, "value": 1}, {"communitynum": 419, "value": 1}, {"communitynum": 420, "value": 1}, {"communitynum": 421, "value": 1}, {"communitynum": 422, "value": 1}, {"communitynum": 423, "value": 1}, {"communitynum": 424, "value": 1}, {"communitynum": 425, "value": 1}, {"communitynum": 426, "value": 1}, {"communitynum": 427, "value": 1}, {"communitynum": 428, "value": 1}, {"communitynum": 429, "value": 1}, {"communitynum": 430, "value": 1}, {"communitynum": 431, "value": 1}, {"communitynum": 432, "value": 1}, {"communitynum": 433, "value": 1}, {"communitynum": 434, "value": 1}, {"communitynum": 435, "value": 1}, {"communitynum": 436, "value": 1}, {"communitynum": 437, "value": 1}, {"communitynum": 438, "value": 1}, {"communitynum": 439, "value": 1}, {"communitynum": 440, "value": 1}, {"communitynum": 441, "value": 1}, {"communitynum": 442, "value": 1}, {"communitynum": 443, "value": 1}, {"communitynum": 444, "value": 1}, {"communitynum": 445, "value": 1}, {"communitynum": 446, "value": 1}, {"communitynum": 447, "value": 1}, {"communitynum": 448, "value": 1}, {"communitynum": 449, "value": 1}, {"communitynum": 450, "value": 1}, {"communitynum": 451, "value": 1}, {"communitynum": 452, "value": 1}, {"communitynum": 453, "value": 1}, {"communitynum": 454, "value": 1}, {"communitynum": 455, "value": 1}, {"communitynum": 456, "value": 1}, {"communitynum": 457, "value": 1}, {"communitynum": 458, "value": 1}, {"communitynum": 459, "value": 1}, {"communitynum": 460, "value": 1}, {"communitynum": 461, "value": 1}, {"communitynum": 462, "value": 1}, {"communitynum": 463, "value": 1}, {"communitynum": 464, "value": 1}, {"communitynum": 465, "value": 1}, {"communitynum": 466, "value": 1}, {"communitynum": 467, "value": 1}, {"communitynum": 468, "value": 1}, {"communitynum": 469, "value": 1}, {"communitynum": 470, "value": 1}, {"communitynum": 471, "value": 1}, {"communitynum": 472, "value": 1}, {"communitynum": 473, "value": 1}, {"communitynum": 474, "value": 1}, {"communitynum": 475, "value": 1}, {"communitynum": 476, "value": 1}, {"communitynum": 477, "value": 1}, {"communitynum": 478, "value": 1}, {"communitynum": 479, "value": 1}, {"communitynum": 480, "value": 1}, {"communitynum": 481, "value": 1}, {"communitynum": 482, "value": 1}, {"communitynum": 483, "value": 1}, {"communitynum": 484, "value": 1}, {"communitynum": 485, "value": 1}, {"communitynum": 486, "value": 1}, {"communitynum": 487, "value": 1}, {"communitynum": 488, "value": 1}, {"communitynum": 489, "value": 1}, {"communitynum": 490, "value": 1}, {"communitynum": 491, "value": 1}, {"communitynum": 492, "value": 1}, {"communitynum": 493, "value": 1}, {"communitynum": 494, "value": 1}, {"communitynum": 495, "value": 1}, {"communitynum": 496, "value": 1}, {"communitynum": 497, "value": 1}, {"communitynum": 498, "value": 1}, {"communitynum": 499, "value": 1}, {"communitynum": 500, "value": 1}, {"communitynum": 501, "value": 1}, {"communitynum": 502, "value": 1}, {"communitynum": 503, "value": 1}, {"communitynum": 504, "value": 1}, {"communitynum": 505, "value": 1}, {"communitynum": 506, "value": 1}, {"communitynum": 507, "value": 1}, {"communitynum": 508, "value": 1}, {"communitynum": 509, "value": 1}, {"communitynum": 510, "value": 1}, {"communitynum": 511, "value": 1}, {"communitynum": 512, "value": 1}, {"communitynum": 513, "value": 1}, {"communitynum": 514, "value": 1}, {"communitynum": 515, "value": 1}, {"communitynum": 516, "value": 1}, {"communitynum": 517, "value": 1}, {"communitynum": 518, "value": 1}, {"communitynum": 519, "value": 1}, {"communitynum": 520, "value": 1}, {"communitynum": 521, "value": 1}, {"communitynum": 522, "value": 1}, {"communitynum": 523, "value": 1}, {"communitynum": 524, "value": 1}, {"communitynum": 525, "value": 1}, {"communitynum": 526, "value": 1}, {"communitynum": 527, "value": 1}, {"communitynum": 528, "value": 1}, {"communitynum": 529, "value": 1}, {"communitynum": 530, "value": 1}, {"communitynum": 531, "value": 1}, {"communitynum": 532, "value": 1}, {"communitynum": 533, "value": 1}, {"communitynum": 534, "value": 1}, {"communitynum": 535, "value": 1}, {"communitynum": 536, "value": 1}, {"communitynum": 537, "value": 1}, {"communitynum": 538, "value": 1}, {"communitynum": 539, "value": 1}, {"communitynum": 540, "value": 1}, {"communitynum": 541, "value": 1}, {"communitynum": 542, "value": 1}, {"communitynum": 543, "value": 1}, {"communitynum": 544, "value": 1}, {"communitynum": 545, "value": 1}, {"communitynum": 546, "value": 1}, {"communitynum": 547, "value": 1}, {"communitynum": 548, "value": 1}, {"communitynum": 549, "value": 1}, {"communitynum": 550, "value": 1}, {"communitynum": 551, "value": 1}, {"communitynum": 552, "value": 1}, {"communitynum": 553, "value": 1}, {"communitynum": 554, "value": 1}, {"communitynum": 555, "value": 1}, {"communitynum": 556, "value": 1}, {"communitynum": 557, "value": 1}, {"communitynum": 558, "value": 1}, {"communitynum": 559, "value": 1}, {"communitynum": 560, "value": 1}, {"communitynum": 561, "value": 1}, {"communitynum": 562, "value": 1}, {"communitynum": 563, "value": 1}, {"communitynum": 564, "value": 1}, {"communitynum": 565, "value": 1}, {"communitynum": 566, "value": 1}, {"communitynum": 567, "value": 1}, {"communitynum": 568, "value": 1}, {"communitynum": 569, "value": 1}, {"communitynum": 570, "value": 1}, {"communitynum": 571, "value": 1}, {"communitynum": 572, "value": 1}, {"communitynum": 573, "value": 1}, {"communitynum": 574, "value": 1}, {"communitynum": 575, "value": 1}, {"communitynum": 576, "value": 1}, {"communitynum": 577, "value": 1}, {"communitynum": 578, "value": 1}, {"communitynum": 579, "value": 1}, {"communitynum": 580, "value": 1}, {"communitynum": 581, "value": 1}, {"communitynum": 582, "value": 1}, {"communitynum": 583, "value": 1}, {"communitynum": 584, "value": 1}, {"communitynum": 585, "value": 1}, {"communitynum": 586, "value": 1}, {"communitynum": 587, "value": 1}, {"communitynum": 588, "value": 1}, {"communitynum": 589, "value": 1}, {"communitynum": 590, "value": 1}, {"communitynum": 591, "value": 1}, {"communitynum": 592, "value": 1}, {"communitynum": 593, "value": 1}, {"communitynum": 594, "value": 1}, {"communitynum": 595, "value": 1}, {"communitynum": 596, "value": 1}, {"communitynum": 597, "value": 1}, {"communitynum": 598, "value": 1}, {"communitynum": 599, "value": 1}, {"communitynum": 600, "value": 1}, {"communitynum": 601, "value": 1}, {"communitynum": 602, "value": 1}, {"communitynum": 603, "value": 1}, {"communitynum": 604, "value": 1}, {"communitynum": 605, "value": 1}, {"communitynum": 606, "value": 1}, {"communitynum": 607, "value": 1}, {"communitynum": 608, "value": 1}, {"communitynum": 609, "value": 1}, {"communitynum": 610, "value": 1}, {"communitynum": 611, "value": 1}, {"communitynum": 612, "value": 1}, {"communitynum": 613, "value": 1}, {"communitynum": 614, "value": 1}, {"communitynum": 615, "value": 1}, {"communitynum": 616, "value": 1}, {"communitynum": 617, "value": 1}, {"communitynum": 618, "value": 1}, {"communitynum": 619, "value": 1}, {"communitynum": 620, "value": 1}, {"communitynum": 621, "value": 1}, {"communitynum": 622, "value": 1}, {"communitynum": 623, "value": 1}, {"communitynum": 624, "value": 1}, {"communitynum": 625, "value": 1}, {"communitynum": 626, "value": 1}, {"communitynum": 627, "value": 1}, {"communitynum": 628, "value": 1}, {"communitynum": 629, "value": 1}, {"communitynum": 630, "value": 1}, {"communitynum": 631, "value": 1}, {"communitynum": 632, "value": 1}, {"communitynum": 633, "value": 1}, {"communitynum": 634, "value": 1}, {"communitynum": 635, "value": 1}, {"communitynum": 636, "value": 1}, {"communitynum": 637, "value": 1}, {"communitynum": 638, "value": 1}, {"communitynum": 639, "value": 1}, {"communitynum": 640, "value": 1}, {"communitynum": 641, "value": 1}, {"communitynum": 642, "value": 1}, {"communitynum": 643, "value": 1}, {"communitynum": 644, "value": 1}, {"communitynum": 645, "value": 1}, {"communitynum": 646, "value": 1}, {"communitynum": 647, "value": 1}, {"communitynum": 648, "value": 1}, {"communitynum": 649, "value": 1}, {"communitynum": 650, "value": 1}, {"communitynum": 651, "value": 1}, {"communitynum": 652, "value": 1}, {"communitynum": 653, "value": 1}, {"communitynum": 654, "value": 1}, {"communitynum": 655, "value": 1}, {"communitynum": 656, "value": 1}, {"communitynum": 657, "value": 1}, {"communitynum": 658, "value": 1}, {"communitynum": 659, "value": 1}, {"communitynum": 660, "value": 1}, {"communitynum": 661, "value": 1}, {"communitynum": 662, "value": 1}, {"communitynum": 663, "value": 1}, {"communitynum": 664, "value": 1}, {"communitynum": 665, "value": 1}, {"communitynum": 666, "value": 1}, {"communitynum": 667, "value": 1}, {"communitynum": 668, "value": 1}, {"communitynum": 669, "value": 1}, {"communitynum": 670, "value": 1}, {"communitynum": 671, "value": 1}, {"communitynum": 672, "value": 1}, {"communitynum": 673, "value": 1}, {"communitynum": 674, "value": 1}, {"communitynum": 675, "value": 1}, {"communitynum": 676, "value": 1}, {"communitynum": 677, "value": 1}, {"communitynum": 678, "value": 1}, {"communitynum": 679, "value": 1}, {"communitynum": 680, "value": 1}, {"communitynum": 681, "value": 1}, {"communitynum": 682, "value": 1}, {"communitynum": 683, "value": 1}, {"communitynum": 684, "value": 1}, {"communitynum": 685, "value": 1}, {"communitynum": 686, "value": 1}, {"communitynum": 687, "value": 1}, {"communitynum": 688, "value": 1}, {"communitynum": 689, "value": 1}, {"communitynum": 690, "value": 1}, {"communitynum": 691, "value": 1}, {"communitynum": 692, "value": 1}, {"communitynum": 693, "value": 1}, {"communitynum": 694, "value": 1}, {"communitynum": 695, "value": 1}, {"communitynum": 696, "value": 1}, {"communitynum": 697, "value": 1}, {"communitynum": 698, "value": 1}, {"communitynum": 699, "value": 1}, {"communitynum": 700, "value": 1}, {"communitynum": 701, "value": 1}, {"communitynum": 702, "value": 1}, {"communitynum": 703, "value": 1}, {"communitynum": 704, "value": 1}, {"communitynum": 705, "value": 1}, {"communitynum": 706, "value": 1}, {"communitynum": 707, "value": 1}, {"communitynum": 708, "value": 1}, {"communitynum": 709, "value": 1}, {"communitynum": 710, "value": 1}, {"communitynum": 711, "value": 1}, {"communitynum": 712, "value": 1}, {"communitynum": 713, "value": 1}, {"communitynum": 714, "value": 1}, {"communitynum": 715, "value": 1}, {"communitynum": 716, "value": 1}, {"communitynum": 717, "value": 1}, {"communitynum": 718, "value": 1}, {"communitynum": 719, "value": 1}, {"communitynum": 720, "value": 1}, {"communitynum": 721, "value": 1}, {"communitynum": 722, "value": 1}, {"communitynum": 723, "value": 1}, {"communitynum": 724, "value": 1}, {"communitynum": 725, "value": 1}, {"communitynum": 726, "value": 1}, {"communitynum": 727, "value": 1}, {"communitynum": 728, "value": 1}, {"communitynum": 729, "value": 1}, {"communitynum": 730, "value": 1}, {"communitynum": 731, "value": 1}, {"communitynum": 732, "value": 1}, {"communitynum": 733, "value": 1}, {"communitynum": 734, "value": 1}, {"communitynum": 735, "value": 1}, {"communitynum": 736, "value": 1}, {"communitynum": 737, "value": 1}, {"communitynum": 738, "value": 1}, {"communitynum": 739, "value": 1}, {"communitynum": 740, "value": 1}, {"communitynum": 741, "value": 1}, {"communitynum": 742, "value": 1}, {"communitynum": 743, "value": 1}, {"communitynum": 744, "value": 1}, {"communitynum": 745, "value": 1}, {"communitynum": 746, "value": 1}, {"communitynum": 747, "value": 1}, {"communitynum": 748, "value": 1}, {"communitynum": 749, "value": 1}, {"communitynum": 750, "value": 1}, {"communitynum": 751, "value": 1}, {"communitynum": 752, "value": 1}, {"communitynum": 753, "value": 1}, {"communitynum": 754, "value": 1}], "edges": [{"source": 0, "target": 3, "value": 45}, {"source": 0, "target": 1, "value": 75}, {"source": 0, "target": 4, "value": 31}, {"source": 0, "target": 5, "value": 15}, {"source": 0, "target": 2, "value": 32}, {"source": 0, "target": 10, "value": 10}, {"source": 0, "target": 8, "value": 32}, {"source": 0, "target": 6, "value": 15}, {"source": 0, "target": 9, "value": 31}, {"source": 0, "target": 12, "value": 6}, {"source": 0, "target": 7, "value": 17}, {"source": 0, "target": 11, "value": 2}, {"source": 3, "target": 7, "value": 22}, {"source": 3, "target": 4, "value": 28}, {"source": 3, "target": 6, "value": 48}, {"source": 3, "target": 5, "value": 23}, {"source": 3, "target": 10, "value": 14}, {"source": 3, "target": 8, "value": 29}, {"source": 3, "target": 11, "value": 8}, {"source": 3, "target": 9, "value": 22}, {"source": 3, "target": 12, "value": 6}, {"source": 1, "target": 3, "value": 69}, {"source": 1, "target": 10, "value": 10}, {"source": 1, "target": 4, "value": 32}, {"source": 1, "target": 5, "value": 19}, {"source": 1, "target": 2, "value": 31}, {"source": 1, "target": 7, "value": 17}, {"source": 1, "target": 8, "value": 26}, {"source": 1, "target": 6, "value": 29}, {"source": 1, "target": 9, "value": 14}, {"source": 1, "target": 12, "value": 4}, {"source": 4, "target": 5, "value": 20}, {"source": 4, "target": 6, "value": 28}, {"source": 4, "target": 11, "value": 2}, {"source": 4, "target": 8, "value": 15}, {"source": 4, "target": 10, "value": 28}, {"source": 4, "target": 7, "value": 41}, {"source": 4, "target": 9, "value": 20}, {"source": 4, "target": 12, "value": 10}, {"source": 5, "target": 8, "value": 14}, {"source": 5, "target": 10, "value": 27}, {"source": 5, "target": 6, "value": 32}, {"source": 5, "target": 9, "value": 8}, {"source": 5, "target": 7, "value": 35}, {"source": 5, "target": 11, "value": 2}, {"source": 10, "target": 12, "value": 8}, {"source": 10, "target": 11, "value": 3}, {"source": 2, "target": 5, "value": 24}, {"source": 2, "target": 8, "value": 18}, {"source": 2, "target": 4, "value": 21}, {"source": 2, "target": 6, "value": 14}, {"source": 2, "target": 3, "value": 27}, {"source": 2, "target": 9, "value": 14}, {"source": 2, "target": 10, "value": 10}, {"source": 2, "target": 7, "value": 24}, {"source": 2, "target": 12, "value": 7}, {"source": 2, "target": 11, "value": 1}, {"source": 7, "target": 12, "value": 40}, {"source": 7, "target": 9, "value": 41}, {"source": 7, "target": 10, "value": 30}, {"source": 7, "target": 8, "value": 6}, {"source": 7, "target": 11, "value": 1}, {"source": 8, "target": 11, "value": 2}, {"source": 8, "target": 10, "value": 7}, {"source": 8, "target": 9, "value": 12}, {"source": 8, "target": 12, "value": 8}, {"source": 6, "target": 8, "value": 24}, {"source": 6, "target": 10, "value": 35}, {"source": 6, "target": 7, "value": 54}, {"source": 6, "target": 9, "value": 23}, {"source": 6, "target": 11, "value": 4}, {"source": 6, "target": 12, "value": 23}, {"source": 11, "target": 12, "value": 1}, {"source": 9, "target": 10, "value": 19}, {"source": 9, "target": 12, "value": 16}, {"source": 9, "target": 11, "value": 3}]}